cloudconnect2/__init__.py
cloudconnect2/cloudconnect2.py
cloudconnect2-0.1.2.dist-info/LICENSE
cloudconnect2-0.1.2.dist-info/METADATA
cloudconnect2-0.1.2.dist-info/WHEEL
cloudconnect2-0.1.2.dist-info/top_level.txt
cloudconnect2-0.1.2.dist-info/RECORD
