Metadata-Version: 2.1
Name: cloudconnect2
Version: 0.1.2
Summary: A package to connect retrieve the API credentials in SAP BTP
Author: Joel Kischkel
Author-email: joel.kischkel@syntax.com
License: MIT
License-File: LICENSE
Requires-Dist: requests
Requires-Dist: cfenv
